Metadata-Version: 2.1
Name: appcenter-tool
Version: 0.3
Summary: Helper to trigger appcenterbuild
Home-page: https://bitbucket.org/celadonteam/appcenter-build
Author: Celadon Developers
Author-email: opensource@celadon.ae
License: MIT
Platform: any
Requires-Python: >=3.6
